{
  "id": "3318114",
  "name": "netease",
  "font_family": "iconfont",
  "css_prefix_text": "icon-",
  "description": "",
  "glyphs": [
    {
      "icon_id": "2076218",
      "name": "播放2",
      "font_class": "bofang",
      "unicode": "e87c",
      "unicode_decimal": 59516
    },
    {
      "icon_id": "7594048",
      "name": "24gl-play",
      "font_class": "24gl-play",
      "unicode": "ea6d",
      "unicode_decimal": 60013
    },
    {
      "icon_id": "201588",
      "name": "3.1列表",
      "font_class": "31liebiao",
      "unicode": "e600",
      "unicode_decimal": 58880
    },
    {
      "icon_id": "1304951",
      "name": "列表",
      "font_class": "liebiao",
      "unicode": "e62d",
      "unicode_decimal": 58925
    },
    {
      "icon_id": "1718325",
      "name": "日历3",
      "font_class": "rili",
      "unicode": "e601",
      "unicode_decimal": 58881
    },
    {
      "icon_id": "2674483",
      "name": "暂停",
      "font_class": "zanting",
      "unicode": "e62a",
      "unicode_decimal": 58922
    },
    {
      "icon_id": "5387900",
      "name": "搜索_o",
      "font_class": "sousuo_o",
      "unicode": "eb86",
      "unicode_decimal": 60294
    },
    {
      "icon_id": "6688666",
      "name": "排行榜",
      "font_class": "paihangbang--",
      "unicode": "e610",
      "unicode_decimal": 58896
    },
    {
      "icon_id": "7594051",
      "name": "24gl-playCircle",
      "font_class": "24gl-playCircle",
      "unicode": "ea6e",
      "unicode_decimal": 60014
    },
    {
      "icon_id": "10487575",
      "name": "收音机",
      "font_class": "shouyinji",
      "unicode": "e69d",
      "unicode_decimal": 59037
    },
    {
      "icon_id": "14720513",
      "name": "歌单",
      "font_class": "gedan",
      "unicode": "e61b",
      "unicode_decimal": 58907
    }
  ]
}
